bianbu_ai_toolkit-1.0.6.data/scripts/bianbu
jdsk/__init__.py
jdsk/utils.py
jdsk/wrapper.py
jdsk/converter/__init__.py
jdsk/converter/argsparser.py
jdsk/converter/caffe2jdsk.py
jdsk/converter/onnx2jdsk.py
jdsk/converter/paddle2jdsk.py
jdsk/converter/tf2jdsk.py
jdsk/converter/tf_loader.py
jdsk/helper/__init__.py
jdsk/helper/check_precision.py
jdsk/helper/cnpy_helper.py
jdsk/helper/create_test_dir.py
jdsk/helper/model_helper.py
jdsk/simulator/__init__.py
jdsk/simulator/test.py
bianbu_ai_toolkit-1.0.6.dist-info/METADATA
bianbu_ai_toolkit-1.0.6.dist-info/WHEEL
bianbu_ai_toolkit-1.0.6.dist-info/entry_points.txt
bianbu_ai_toolkit-1.0.6.dist-info/top_level.txt
bianbu_ai_toolkit-1.0.6.dist-info/RECORD
